{"details": [{"n": "A Country Practice", "r": 6.8, "v": 523, "y": "1981", "ec": 1058}], "ratings": [{"r": 7.4, "v": 6, "en": "A Fair Cop: Part 1", "eid": "tt0548974", "eno": 81, "sno": 12}, {"r": 8.6, "v": 6, "en": "A Lady's Choice: Part 1", "eid": "tt0548994", "eno": 45, "sno": 3}, {"r": 7.4, "v": 5, "en": "A Question of Attitude: Part 1", "eid": "tt0549006", "eno": 75, "sno": 6}, {"r": 7.0, "v": 5, "en": "A Question of Attitude: Part 2", "eid": "tt0549007", "eno": 76, "sno": 6}, {"r": 8.4, "v": 7, "en": "A Virtuous Woman: Part 1", "eid": "tt0549018", "eno": 55, "sno": 12}, {"r": 7.2, "v": 6, "en": "Agoraphobic Sons and Lovers: Part 1", "eid": "tt0549024", "eno": 9, "sno": 2}, {"r": 8.4, "v": 6, "en": "All Fired Up: Part 1", "eid": "tt0549032", "eno": 53, "sno": 3}, {"r": 8.4, "v": 6, "en": "All Fired Up: Part 2", "eid": "tt0549033", "eno": 54, "sno": 3}, {"r": 8.7, "v": 7, "en": "Alternatives: Part 1", "eid": "tt0549036", "eno": 13, "sno": 1}, {"r": 8.7, "v": 7, "en": "Alternatives: Part 2", "eid": "tt0549037", "eno": 14, "sno": 1}, {"r": 8.2, "v": 6, "en": "Beating Around the Bush: Part 1", "eid": "tt0549050", "eno": 19, "sno": 2}, {"r": 8.2, "v": 6, "en": "Beating Around the Bush: Part 2", "eid": "tt0549051", "eno": 20, "sno": 2}, {"r": 8.0, "v": 5, "en": "Bigger Than Texas: Part 1", "eid": "tt0549059", "eno": 25, "sno": 11}, {"r": 8.7, "v": 7, "en": "Coming Home: Part 1", "eid": "tt0549100", "eno": 9, "sno": 1}, {"r": 8.7, "v": 7, "en": "Coming Home: Part 2", "eid": "tt0549101", "eno": 10, "sno": 1}, {"r": 8.6, "v": 6, "en": "Elementary Miss Watson: Part 2", "eid": "tt0549140", "eno": 20, "sno": 4}, {"r": 7.8, "v": 6, "en": "Follow the Leader: Part 1", "eid": "tt0549166", "eno": 1, "sno": 5}, {"r": 7.8, "v": 6, "en": "Follow the Leader: Part 2", "eid": "tt0549167", "eno": 2, "sno": 5}, {"r": 8.4, "v": 6, "en": "From This Day Forward: Part 1", "eid": "tt0549178", "eno": 77, "sno": 3}, {"r": 9.0, "v": 8, "en": "From This Day Forward: Part 2", "eid": "tt0549179", "eno": 78, "sno": 3}, {"r": 8.2, "v": 6, "en": "Golden Fleece: Part 1", "eid": "tt0549188", "eno": 1, "sno": 2}, {"r": 8.2, "v": 6, "en": "Golden Fleece: Part 2", "eid": "tt0549189", "eno": 2, "sno": 2}, {"r": 8.0, "v": 5, "en": "Heartbreaker: Part 1", "eid": "tt0549206", "eno": 1, "sno": 12}, {"r": 7.8, "v": 5, "en": "Hot and Cold: Part 1", "eid": "tt0549221", "eno": 35, "sno": 11}, {"r": 8.4, "v": 6, "en": "I Know Where She's Gone: Part 1", "eid": "tt0549224", "eno": 11, "sno": 2}, {"r": 8.4, "v": 6, "en": "I Know Where She's Gone: Part 2", "eid": "tt0549225", "eno": 12, "sno": 2}, {"r": 7.8, "v": 12, "en": "In General Practice: Part 1", "eid": "tt0549230", "eno": 1, "sno": 1}, {"r": 8.6, "v": 11, "en": "In General Practice: Part 2", "eid": "tt0549231", "eno": 2, "sno": 1}, {"r": 8.4, "v": 10, "en": "It's My Party: Part 1", "eid": "tt0549238", "eno": 59, "sno": 12}, {"r": 8.1, "v": 9, "en": "It's My Party: Part 2", "eid": "tt0549239", "eno": 60, "sno": 12}, {"r": 7.2, "v": 5, "en": "Last of the Summer Wine: Part 1", "eid": "tt0549250", "eno": 15, "sno": 9}, {"r": 7.7, "v": 6, "en": "Last of the Summer Wine: Part 2", "eid": "tt0549251", "eno": 16, "sno": 9}, {"r": 8.2, "v": 7, "en": "Learning the Lessons: Part 1", "eid": "tt0549254", "eno": 5, "sno": 8}, {"r": 8.3, "v": 7, "en": "Learning the Lessons: Part 2", "eid": "tt0549255", "eno": 6, "sno": 8}, {"r": 7.6, "v": 5, "en": "Little Big Man: Part 2", "eid": "tt0549259", "eno": 62, "sno": 10}, {"r": 9.0, "v": 9, "en": "Mates: Part 1", "eid": "tt0549280", "eno": 7, "sno": 2}, {"r": 9.0, "v": 9, "en": "Mates: Part 2", "eid": "tt0549281", "eno": 8, "sno": 2}, {"r": 8.8, "v": 6, "en": "My Son, My Son: Part 1", "eid": "tt0549290", "eno": 65, "sno": 3}, {"r": 8.2, "v": 6, "en": "Never Called Me Mother: Part 1", "eid": "tt0549296", "eno": 21, "sno": 2}, {"r": 8.2, "v": 6, "en": "Never Called Me Mother: Part 2", "eid": "tt0549297", "eno": 22, "sno": 2}, {"r": 8.3, "v": 6, "en": "One Man's Poison: Part 2", "eid": "tt0549333", "eno": 12, "sno": 13}, {"r": 7.8, "v": 5, "en": "Paying the Price: Part 1", "eid": "tt0549350", "eno": 77, "sno": 11}, {"r": 8.7, "v": 25, "en": "Repairing the Damage: Part 2", "eid": "tt0549384", "eno": 44, "sno": 4}, {"r": 8.7, "v": 23, "en": "Repairing the Damage: Part 1", "eid": "tt0549385", "eno": 43, "sno": 4}, {"r": 8.7, "v": 7, "en": "Secrets: Part 1", "eid": "tt0549404", "eno": 11, "sno": 1}, {"r": 8.7, "v": 7, "en": "Secrets: Part 2", "eid": "tt0549406", "eno": 12, "sno": 1}, {"r": 8.0, "v": 6, "en": "Shootin' Through: Part 1", "eid": "tt0549416", "eno": 23, "sno": 2}, {"r": 8.0, "v": 6, "en": "Shootin' Through: Part 2", "eid": "tt0549417", "eno": 24, "sno": 2}, {"r": 7.2, "v": 5, "en": "Sleeping Beauty: Part 1", "eid": "tt0549424", "eno": 37, "sno": 12}, {"r": 5.8, "v": 5, "en": "Sleeping Beauty: Part 2", "eid": "tt0549425", "eno": 38, "sno": 12}, {"r": 8.7, "v": 7, "en": "Suffer Little Children: Part 1", "eid": "tt0549456", "eno": 5, "sno": 2}, {"r": 8.4, "v": 6, "en": "Team Work: Part 1", "eid": "tt0549468", "eno": 3, "sno": 2}, {"r": 7.8, "v": 5, "en": "The Facts of Life: Part 2", "eid": "tt0549475", "eno": 38, "sno": 11}, {"r": 8.8, "v": 6, "en": "The Itinerants: Part 1", "eid": "tt0549490", "eno": 5, "sno": 1}, {"r": 8.8, "v": 6, "en": "The Itinerants: Part 2", "eid": "tt0549491", "eno": 6, "sno": 1}, {"r": 8.2, "v": 6, "en": "The Sentimental Bloke: Part 1", "eid": "tt0549520", "eno": 43, "sno": 3}, {"r": 8.8, "v": 6, "en": "They Shoot Cows Don't They: Part 1", "eid": "tt0549530", "eno": 7, "sno": 1}, {"r": 8.8, "v": 6, "en": "They Shoot Cows Don't They: Part 2", "eid": "tt0549531", "eno": 8, "sno": 1}, {"r": 8.7, "v": 8, "en": "Town Tragedy: Part 1", "eid": "tt0549538", "eno": 3, "sno": 1}, {"r": 8.7, "v": 8, "en": "Town Tragedy: Part 2", "eid": "tt0549539", "eno": 4, "sno": 1}, {"r": 8.0, "v": 5, "en": "The Two of Us: Part 2", "eid": "tt0549561", "eno": 2, "sno": 11}, {"r": 8.8, "v": 6, "en": "Warning Signs: Part 2", "eid": "tt0549571", "eno": 30, "sno": 3}, {"r": 7.8, "v": 5, "en": "Where the Wild Things Are: Part 2", "eid": "tt0549587", "eno": 36, "sno": 12}, {"r": 8.3, "v": 6, "en": "Mozart Rules: Part 2", "eid": "tt0944348", "eno": 62, "sno": 7}, {"r": 8.4, "v": 5, "en": "Molly: Part 2", "eid": "tt1004114", "eno": 32, "sno": 5}, {"r": 8.0, "v": 5, "en": "Fighting Back: Part 1", "eid": "tt1035963", "eno": 15, "sno": 6}, {"r": 7.8, "v": 6, "en": "Race, Greed and Colour: Part 2", "eid": "tt1035974", "eno": 32, "sno": 6}, {"r": 8.0, "v": 6, "en": "Revelations: Part 1", "eid": "tt1097880", "eno": 7, "sno": 8}, {"r": 8.2, "v": 6, "en": "Revelations: Part 2", "eid": "tt1097881", "eno": 8, "sno": 8}, {"r": 7.8, "v": 6, "en": "Revelations: Part 3", "eid": "tt1097882", "eno": 9, "sno": 8}, {"r": 8.0, "v": 6, "en": "Revelations: Part 4", "eid": "tt1097883", "eno": 10, "sno": 8}, {"r": 8.0, "v": 6, "en": "Give Me Shelter: Part 1", "eid": "tt1190251", "eno": 45, "sno": 9}, {"r": 7.4, "v": 6, "en": "Play It Again: Part 1", "eid": "tt1190267", "eno": 7, "sno": 9}, {"r": 7.2, "v": 6, "en": "Sanctuary: Part 2", "eid": "tt1190272", "eno": 2, "sno": 9}, {"r": 7.2, "v": 6, "en": "A Private Concern: Part 1", "eid": "tt1191253", "eno": 53, "sno": 10}, {"r": 6.4, "v": 6, "en": "A Private Concern: Part 2", "eid": "tt1191254", "eno": 54, "sno": 10}, {"r": 7.8, "v": 6, "en": "Ain't Misbehaving: Part 1", "eid": "tt1191259", "eno": 81, "sno": 10}, {"r": 7.8, "v": 6, "en": "Eye of the Beholder: Part 1", "eid": "tt1191278", "eno": 77, "sno": 10}, {"r": 7.8, "v": 6, "en": "My Sisters's Keeper: Part 1", "eid": "tt1191290", "eno": 83, "sno": 10}, {"r": 7.8, "v": 6, "en": "My Sisters's Keeper: Part 2", "eid": "tt1191291", "eno": 84, "sno": 10}]}
