{"details": [{"n": "Rob Riggle Global Investigator", "r": 7.3, "v": 139, "y": "2019", "ec": 6}], "ratings": [{"r": 7.1, "v": 16, "en": "The Atlantis Case", "eid": "tt11947506", "eno": 1, "sno": 1}, {"r": 6.5, "v": 12, "en": "The Holiest of Grails", "eid": "tt11947512", "eno": 2, "sno": 1}, {"r": 7.3, "v": 7, "en": "The Mystery of the O.K. Corral", "eid": "tt12113394", "eno": 4, "sno": 1}, {"r": 7.9, "v": 7, "en": "Pirate Booty", "eid": "tt12126308", "eno": 3, "sno": 1}, {"r": 7.6, "v": 5, "en": "Really Close Encounters", "eid": "tt12310826", "eno": 6, "sno": 1}]}
