{"details": [{"n": "Stillwater", "r": 8.4, "v": 225, "y": "2020", "ec": 6}], "ratings": [{"r": 8.5, "v": 19, "en": "The Impossible Dream/Stuck in the Rain", "eid": "tt13140544", "eno": 1, "sno": 1}, {"r": 8.2, "v": 8, "en": "Gift of Compassion/Larger Than Life", "eid": "tt13596700", "eno": 2, "sno": 1}, {"r": 8.4, "v": 7, "en": "Soaked/A Perfect Fit", "eid": "tt13596708", "eno": 3, "sno": 1}, {"r": 7.8, "v": 6, "en": "Downward Dog/The Sleeping Moon", "eid": "tt13596720", "eno": 4, "sno": 1}, {"r": 8.3, "v": 7, "en": "The Race/Dressed Up", "eid": "tt13596730", "eno": 5, "sno": 1}, {"r": 8.4, "v": 7, "en": "The Haircut/Paper Wings", "eid": "tt13596738", "eno": 6, "sno": 1}]}
