{"details": [{"n": "Fan Questions", "r": 8.5, "v": 7, "y": "2021", "ec": 7}], "ratings": [{"r": 6.7, "v": 32, "en": "Scarlett Johansson and Florence Pugh Answer Fan Questions", "eid": "tt14954394", "eno": 1, "sno": 1}, {"r": 7.0, "v": 6, "en": "The Cast of Outer Banks Answers Your Burning Questions", "eid": "tt15045538", "eno": 2, "sno": 1}, {"r": 8.3, "v": 20, "en": "Tom Ellis Answers IMDb Fan Questions", "eid": "tt15094598", "eno": 3, "sno": 1}, {"r": 9.0, "v": 9, "en": "The Walking Dead Cast Answers IMDb Fan Questions", "eid": "tt15100672", "eno": 4, "sno": 1}, {"r": 6.1, "v": 9, "en": "Ryan Reynolds and Jodie Comer Answer IMDb Fan Questions", "eid": "tt15203094", "eno": 5, "sno": 1}]}
