{"details": [{"n": "For All Mankind", "r": 7.8, "v": 19711, "y": "2019", "ec": 23}], "ratings": [{"r": 8.1, "v": 676, "en": "Every Little Thing", "eid": "tt11128080", "eno": 1, "sno": 2}, {"r": 7.8, "v": 436, "en": "Best-Laid Plans", "eid": "tt11747988", "eno": 6, "sno": 2}, {"r": 7.8, "v": 472, "en": "Don't Be Cruel", "eid": "tt11784180", "eno": 7, "sno": 2}, {"r": 8.2, "v": 609, "en": "Rules of Engagement", "eid": "tt11879782", "eno": 3, "sno": 2}, {"r": 8.1, "v": 492, "en": "And Here's to You", "eid": "tt11904060", "eno": 8, "sno": 2}, {"r": 7.8, "v": 505, "en": "Pathfinder", "eid": "tt12076928", "eno": 4, "sno": 2}, {"r": 9.0, "v": 644, "en": "Triage", "eid": "tt13351084", "eno": 9, "sno": 2}, {"r": 9.6, "v": 1379, "en": "The Grey", "eid": "tt13351086", "eno": 10, "sno": 2}, {"r": 7.4, "v": 534, "en": "The Bleeding Edge", "eid": "tt13417002", "eno": 2, "sno": 2}, {"r": 7.5, "v": 457, "en": "The Weight", "eid": "tt13417004", "eno": 5, "sno": 2}, {"r": 7.7, "v": 1294, "en": "Red Moon", "eid": "tt9198004", "eno": 1, "sno": 1}, {"r": 7.8, "v": 1058, "en": "He Built the Saturn V", "eid": "tt9198018", "eno": 2, "sno": 1}, {"r": 8.1, "v": 895, "en": "Prime Crew", "eid": "tt9248524", "eno": 4, "sno": 1}, {"r": 8.3, "v": 858, "en": "Rupture", "eid": "tt9287940", "eno": 8, "sno": 1}, {"r": 7.9, "v": 791, "en": "Home Again", "eid": "tt9433040", "eno": 6, "sno": 1}, {"r": 8.2, "v": 829, "en": "Hi Bob", "eid": "tt9471544", "eno": 7, "sno": 1}, {"r": 8.6, "v": 954, "en": "Into the Abyss", "eid": "tt9524520", "eno": 5, "sno": 1}, {"r": 9.1, "v": 985, "en": "A City Upon a Hill", "eid": "tt9537026", "eno": 10, "sno": 1}, {"r": 8.9, "v": 936, "en": "Bent Bird", "eid": "tt9614932", "eno": 9, "sno": 1}, {"r": 8.1, "v": 1045, "en": "Nixon's Women", "eid": "tt9814596", "eno": 3, "sno": 1}]}
