{"details": [{"n": "Creepshow", "r": 7.1, "v": 5221, "y": "2019", "ec": 16}], "ratings": [{"r": 7.9, "v": 527, "en": "Model Kid/Public Television of the Dead", "eid": "tt13669842", "eno": 1, "sno": 2}, {"r": 6.7, "v": 347, "en": "Dead and Breakfast/Pesticide", "eid": "tt14035372", "eno": 2, "sno": 2}, {"r": 6.6, "v": 337, "en": "The Right Snuff/Sibling Rivalry", "eid": "tt14363734", "eno": 3, "sno": 2}, {"r": 6.5, "v": 259, "en": "Pipe Screams/Within the Walls of Madness", "eid": "tt14363740", "eno": 4, "sno": 2}, {"r": 7.3, "v": 269, "en": "Night of the Living Late Show", "eid": "tt14363748", "eno": 5, "sno": 2}, {"r": 7.2, "v": 1338, "en": "Gray Matter/The House of the Head", "eid": "tt9597124", "eno": 1, "sno": 1}, {"r": 7.0, "v": 1032, "en": "Bad Wolf Down/The Finger", "eid": "tt9597126", "eno": 2, "sno": 1}, {"r": 7.5, "v": 955, "en": "All Hallow's Eve/The Man in the Suitcase", "eid": "tt9597132", "eno": 3, "sno": 1}, {"r": 6.5, "v": 722, "en": "Night of the Paw/Times Is Tough in Musky Holler", "eid": "tt9597134", "eno": 5, "sno": 1}, {"r": 6.9, "v": 800, "en": "The Companion/Lydia Layne's Better Half", "eid": "tt9597136", "eno": 4, "sno": 1}, {"r": 7.1, "v": 685, "en": "Skincrawlers/By the Silver Water of Lake Champlain", "eid": "tt9597142", "eno": 6, "sno": 1}]}
