{"details": [{"n": "Mafia Killers with Colin McLaren", "r": 6.8, "v": 17, "y": "2018", "ec": 6}], "ratings": [{"r": 6.8, "v": 8, "en": "John Gotti - The Teflon Don", "eid": "tt8924944", "eno": 1, "sno": 1}, {"r": 6.4, "v": 8, "en": "Sammy 'The Bull' Gravano", "eid": "tt8963132", "eno": 2, "sno": 1}, {"r": 6.4, "v": 8, "en": "Carmine The Snake Persico", "eid": "tt8963140", "eno": 3, "sno": 1}, {"r": 6.0, "v": 5, "en": "Anthony 'Gaspipe' Casso", "eid": "tt8963152", "eno": 4, "sno": 1}, {"r": 6.4, "v": 7, "en": "Henry Hill 'The Goodfella'", "eid": "tt8963164", "eno": 5, "sno": 1}]}
