{"details": [{"n": "Private Penthouse", "r": 7.3, "v": 18, "y": "2001", "ec": 12}], "ratings": [{"r": 7.4, "v": 77, "en": "Private Penthouse Movies 1: Call Girl", "eid": "tt0233403", "eno": 1, "sno": 1}, {"r": 7.2, "v": 32, "en": "Fashion", "eid": "tt0233706", "eno": 2, "sno": 1}, {"r": 8.1, "v": 90, "en": "Dangerous Things", "eid": "tt0255090", "eno": 3, "sno": 1}, {"r": 8.1, "v": 57, "en": "Dangerous Things 2", "eid": "tt0255091", "eno": 4, "sno": 1}, {"r": 7.4, "v": 52, "en": "Private Penthouse Movies 5: Italian Flair", "eid": "tt0260976", "eno": 5, "sno": 1}, {"r": 8.3, "v": 40, "en": "Sex Opera", "eid": "tt0313582", "eno": 1, "sno": 2}, {"r": 7.7, "v": 14, "en": "Eve, Insane Obsession", "eid": "tt0413157", "eno": 2, "sno": 2}, {"r": 6.5, "v": 17, "en": "The Last Muse", "eid": "tt0413159", "eno": 6, "sno": 1}, {"r": 7.1, "v": 19, "en": "Too Many Women for a Man", "eid": "tt0413160", "eno": 5, "sno": 2}, {"r": 6.0, "v": 11, "en": "Without Limits: Sex Out Of Control", "eid": "tt0413161", "eno": 4, "sno": 2}, {"r": 8.1, "v": 12, "en": "Without Limits 2", "eid": "tt0413162", "eno": 6, "sno": 2}]}
